cel/__init__.py
cel/assets/celai_connectors.png
cel/assets/celai_diagram.png
cel/assets/celai_middlewares.png
cel/assets/celai_router_diagram.png
cel/assets/celia_logo.png
cel/assets/celia_overview1.png
cel/assistants/base_assistant.py
cel/assistants/common.py
cel/assistants/context.py
cel/assistants/function_context.py
cel/assistants/function_response.py
cel/assistants/macaw/custom_chat_models/chat_open_router.py
cel/assistants/macaw/macaw_assistant.py
cel/assistants/macaw/macaw_history_adapter.py
cel/assistants/macaw/macaw_inference_context.py
cel/assistants/macaw/macaw_nlp.py
cel/assistants/macaw/macaw_settings.py
cel/assistants/macaw/macaw_test_chat_model.py
cel/assistants/macaw/macaw_utils.py
cel/assistants/request_context.py
cel/assistants/router/agentic_router.py
cel/assistants/router/logic_router.py
cel/assistants/router/utils.py
cel/assistants/state_manager.py
cel/assistants/stream_content_chunk.py
cel/cache.py
cel/comms/client_command.py
cel/comms/sentense_detection.py
cel/comms/utils.py
cel/config.py
cel/connectors/cli/cli_connector.py
cel/connectors/cli/model/cli_lead.py
cel/connectors/cli/model/cli_message.py
cel/connectors/livekit/livekit_adapter.py
cel/connectors/livekit/livekit_connector.py
cel/connectors/livekit/model/livekit_lead.py
cel/connectors/livekit/model/livekit_message.py
cel/connectors/telegram/__init__.py
cel/connectors/telegram/model/telegram_attachment.py
cel/connectors/telegram/model/telegram_lead.py
cel/connectors/telegram/model/telegram_message.py
cel/connectors/telegram/run_mode.py
cel/connectors/telegram/samples/hi.mp3
cel/connectors/telegram/samples/hi.oga
cel/connectors/telegram/samples/hi.ogg
cel/connectors/telegram/samples/message.json
cel/connectors/telegram/samples/message_audio.json
cel/connectors/telegram/samples/message_callback_query.json
cel/connectors/telegram/samples/message_img.json
cel/connectors/telegram/samples/message_imgx2.json
cel/connectors/telegram/samples/message_location.json
celai-0.6.9.dist-info/METADATA
celai-0.6.9.dist-info/WHEEL
celai-0.6.9.dist-info/licenses/LICENSE
celai-0.6.9.dist-info/RECORD
