Metadata-Version: 2.4
Name: celai
Version: 0.6.9
Summary: AI Driven Communication Platform. Assistants made easy.
License-File: LICENSE
Author: Alex Martin
Author-email: alejamp@gmail.com
Requires-Python: >=3.11,<4.0
Classifier: License :: OSI Approved :: MIT License
Classifier: Operating System :: OS Independent
Classifier: Programming Language :: Python :: 3
Classifier: Programming Language :: Python :: 3.11
Classifier: Programming Language :: Python :: 3.12
Classifier: Programming Language :: Python :: 3.13
Classifier: Programming Language :: Python :: 3.14
Requires-Dist: PyJWT (>=2.10.1)
Requires-Dist: aiogram (>=3.6.0)
Requires-Dist: aioredis (>=2.0.1)
Requires-Dist: beautifulsoup4 (>=4.12.3)
Requires-Dist: chardet (>=5.2.0)
Requires-Dist: chromadb (>=0.5.0)
Requires-Dist: cryptography (>=44.0.0)
Requires-Dist: deepgram-sdk (>=3.2.7)
Requires-Dist: dictdiffer (>=0.9.0)
Requires-Dist: diskcache (>=5.6.3)
Requires-Dist: elevenlabs (>=1.9.0)
Requires-Dist: fakeredis (>=2.23.2)
Requires-Dist: geopy (>=2.4.1)
Requires-Dist: halo (>=0.0.31)
Requires-Dist: langchain (>=0.2.0)
Requires-Dist: langchain-chroma (>=0.1.1)
Requires-Dist: langchain-community (>=0.2.1)
Requires-Dist: langchain-openai (>=0.1.8)
Requires-Dist: loguru (>=0.7.2)
Requires-Dist: lxml (>=5.2.2)
Requires-Dist: marko (>=2.1.0,<3.0.0)
Requires-Dist: numpy (>=1.26.4)
Requires-Dist: ollama (>=0.3.1)
Requires-Dist: openai (>=1.30.1)
Requires-Dist: openai-responses (>=0.3.2)
Requires-Dist: pybars3 (>=0.9.7)
Requires-Dist: pymongo (>=4.8.0)
Requires-Dist: pysbd (>=0.3.4)
Requires-Dist: python-dotenv (>=1.0.1,<2.0.0)
Requires-Dist: pywa (>=2.7.0)
Requires-Dist: qrcode (>=7.4.2)
Requires-Dist: redis (>=4.6.0)
Requires-Dist: shortuuid (>=1.0.13)
Requires-Dist: together (>=1.2.12)
Project-URL: Homepage, https://github.com/cel-ai/celai
Project-URL: Issues, https://github.com/cel-ai/celai/issues
